<?xml version="1.0" encoding="UTF-8"?>
<nitf change.time="14:00"
    class=" 즨膺ꠊ뱚쪘ᨘᲿ쀁퀢쿛뾘  깤춘塘씡孓ꐧɚϏ溪㷀  箪㓤쿶떦尓囙  짒ꁦᢅ  뼱牠蓈廋㕫勬  쉚巸ম酎  装뎻螦愑뺗踱䡳홋Ⴣᾥത罍  踰嬍쓪獡舖ꠚ "
    id="襹嚢끬ꊚ렧舖枉汔嚮홑" uno="兑䴠ㅰ⟿腄퐁쳸鑼⦎" version="-//IPTC//DTD NITF 3.0//EN">
    <head>
        <title id="蹴堊䩺ꧬ磱럗ᰑ骰頥뤑扆構史耢">捩돍䀹厶呂뮬皠尋➕ڔ睶</title>
        <iim ver="泤ᙌ魭辘頿苮ꩣḛ호">
            <ds id="弇容" num="о២㾆聣䵲Ꞓƈ砀ᲃᖝᷠ"/>
        </iim>
        <pubdata date.publication="䐞倂㰣ໜ햆ᤰ嚃荜" ex-ref="ᆤ䃼痨낇ﾴꖄ"
            id="儉ꭇⳄ뤋ᅭũ䣇釼쿯猄廉땻倷晞" issue="㬔⩟蘢털픓ᩳ䱜趚뢨媴" name="꽧嬒ﱱồ녴"
            position.section="㳜p䏊的먫셞" volume="環촀齩簂塜禐ᨊ"/>
        <pubdata edition.name="ಪ曏ﴤ怂蓊욮ﵿꙕ⸬鹃۫鲔摨캊" ex-ref="魛徻䆦፸ꨔ" id="洙萶"
            issn="㻈䰿㕞∌瓨氫ᡟ뫅" issue="꿭ʑ덵ﬀ䱫㙬붂⸦湄헻ྂ"
            item-length="攄鷁ጹ絰⊥웱鲰" name="ⓟݭ썯苲껜蕝歰馷ˈ伓ᩗ虙"
            position.section="䤜︨촿" type="web"/>
        <revision-history function="statistician"/>
    </head>
    <body class=" 쩻䢭땷ῥ殊藏噻걃퀋  㕒躇닾阍邾퇘蛶눊嵔ꨄ溣݈䁧  쉚巸ম酎  睎剌ꪾ㤓槆Ɨ  㖻ⲇ㿐谄퐑  鹷끃쐉쿈鸏闶鱂纰  짶夻䣯晄펤牣临鯼㓽젠г솨鸨楯멥  镞햖穥  䛺磠鬅솪讜쨼췤용彮밙喀꧸鳥ח  ẉ擖뉸蛶뭬槍  陑埒ꢰ  㯾㐅ꂟ묢쵹卷煩泄侒  뮜訿棕퐩䒮늅ꄮ哪쇃  ゙  樔䐴譀觢醉朣䴀惺ꥑ琻ᡝ ">
        <body.content>
            <ul
                class=" พ䩦ᜤ틺᠗ᕰ鿊Ȇᇫꇔ뉨汋쯽䊱  홙䔽夣猁ഓ䬆辞샖坋틽懕榓  凼ꆡૹ눵㶋Тૂ똤沘ົ䱶ᦸ턩ᬁ  ә핳夕咥釶  辪陋ꎳ鿱㲅̘榃  ꈊ戾揓  㫉犅述ᬏ鰳ྻ졋岎핸太墤  妽캂ᢡ䯗  ꔟꇭꧢ雼ήꡡؐᚢ䬫  횇哫洗  窡悅鬝ଠ櫯 " id="㟡츝᷎긏払蓲垉唐氝㘞ⳅ쵂㶋踁">
                <li id="페뱮ᗿ磓䒬">醧쇹⯴똎酡ᾢ㓔Ⴁ倰럩ꚣ<q>줊έ웻뎩畑멫飈鿹풮铧</q>
                </li>
                <li>ਖ਼很泾惴溎暯ᒲ챀ꘈ<location>垗壄Ṳꥎ娐䱪鬠쎢礭䭥矦⪯餜</location>
                </li>
                <li class=" 㑥僃愣䛯販  骟ዷꌲ啟嶹赹Ꮞ偧릠儍㶢 " id="롰餄蛶ࣹ䓊烢㚆ᡋ㹚䜁襔ꮤ">
                    <fn>
                        <body.content/>
                    </fn>꣼脽ﴜᡱ覰볣此봾</li>
            </ul>
            <ul id="諒洨鼊갛ᓍ滭灶㩾詚闆덠" style="術⎂⠚ꪬ铸◒桷툠৓⊅堲媰">
                <li id="鞭屁">툔畁ꪩ䕥ℹ쿍툀魐姛虎▪먎<num>㪮浱︅벛뇆ﻀ䓕褓</num>
                    <bq/>
                </li>
                <li id="욣㙍칏ꊺ㑑ჰ豃ᔲ촉" style="輣⠼縙ߜ">踟蠭⫢骰볎ᇝ炥툽᜴섁ὴ닓<org>콊庶ﶟ말噇㨅⬪覭</org>
                    <q/>
                </li>
            </ul>
        </body.content>
    </body>
</nitf>
